pip_system_certs.pth
pip_system_certs/__init__.py
pip_system_certs/__version__.py
pip_system_certs/bootstrap.py
pip_system_certs/wrapt_requests.py
pip_system_certs-5.1.dist-info/licenses/LICENSE
pip_system_certs-5.1.dist-info/METADATA
pip_system_certs-5.1.dist-info/WHEEL
pip_system_certs-5.1.dist-info/top_level.txt
pip_system_certs-5.1.dist-info/RECORD
