Metadata-Version: 2.4
Name: pip_system_certs
Version: 5.1
Summary: Automatically configures Python to use system certificates via truststore
Author-email: Andrew Leech <andrew@alelec.net>
License-Expression: BSD-3-Clause
Project-URL: Homepage, https://gitlab.com/alelec/pip-system-certs
Project-URL: Repository, https://gitlab.com/alelec/pip-system-certs
Project-URL: Issues, https://gitlab.com/alelec/pip-system-certs/-/issues
Classifier: Development Status :: 4 - Beta
Classifier: Intended Audience :: Developers
Classifier: Programming Language :: Python :: 3
Classifier: Programming Language :: Python :: 3.10
Classifier: Programming Language :: Python :: 3.11
Classifier: Programming Language :: Python :: 3.12
Classifier: Programming Language :: Python :: 3.13
Classifier: Topic :: Software Development :: Libraries :: Python Modules
Classifier: Topic :: System :: Systems Administration
Classifier: Topic :: Security :: Cryptography
Requires-Python: >=3.10
License-File: LICENSE
Requires-Dist: pip>=24.2
Dynamic: license-file
